threedvector/__init__.py
threedvector/threedvector.py
threedvector-0.3.3.dist-info/LICENSE.txt
threedvector-0.3.3.dist-info/METADATA
threedvector-0.3.3.dist-info/WHEEL
threedvector-0.3.3.dist-info/top_level.txt
threedvector-0.3.3.dist-info/RECORD
