Metadata-Version: 2.1
Name: threedvector
Version: 0.3.3
Summary: A package to work with 3D vectors in Spherical and Cartesian coordinates.
Home-page: https://gitlab.com/gpaul.nel/threedvector
Author: Paul Nel
Author-email: gpaul.nel@gmail.com
License: UNKNOWN
Platform: UNKNOWN
Classifier: Programming Language :: Python :: 3
Classifier: License :: OSI Approved :: MIT License
Classifier: Operating System :: OS Independent
